arcade_hubspot_marketing_api/__init__.py
arcade_hubspot_marketing_api/moar/Hubspot_Marketing.json
arcade_hubspot_marketing_api/moar/openapi.json
arcade_hubspot_marketing_api/tools/__init__.py
arcade_hubspot_marketing_api/tools/request_body_schemas.py
arcade_hubspot_marketing_api/wrapper_tools/AddCampaignBudgetItem.json
arcade_hubspot_marketing_api/wrapper_tools/ArchiveCampaignsBatch.json
arcade_hubspot_marketing_api/wrapper_tools/ArchiveMarketingForm.json
arcade_hubspot_marketing_api/wrapper_tools/AssociateAssetWithCampaign.json
arcade_hubspot_marketing_api/wrapper_tools/AssociateListWithMarketingEvent.json
arcade_hubspot_marketing_api/wrapper_tools/CancelMarketingEvent.json
arcade_hubspot_marketing_api/wrapper_tools/CloneHubspotEmail.json
arcade_hubspot_marketing_api/wrapper_tools/CreateAbTestEmailVariation.json
arcade_hubspot_marketing_api/wrapper_tools/CreateCampaignSpend.json
arcade_hubspot_marketing_api/wrapper_tools/CreateMarketingCampaign.json
arcade_hubspot_marketing_api/wrapper_tools/CreateMarketingCampaignBatch.json
arcade_hubspot_marketing_api/wrapper_tools/CreateMarketingEmail.json
arcade_hubspot_marketing_api/wrapper_tools/CreateMarketingEvent.json
arcade_hubspot_marketing_api/wrapper_tools/CreateMarketingForm.json
arcade_hubspot_marketing_api/wrapper_tools/CreateSmtpApiToken.json
arcade_hubspot_marketing_api/wrapper_tools/DeleteCampaignBudgetItem.json
arcade_hubspot_marketing_api/wrapper_tools/DeleteMarketingCampaign.json
arcade_hubspot_marketing_api/wrapper_tools/DeleteMarketingEmail.json
arcade_hubspot_marketing_api/wrapper_tools/DeleteMarketingEvent.json
arcade_hubspot_marketing_api/wrapper_tools/DeleteMarketingEvents.json
arcade_hubspot_marketing_api/wrapper_tools/DeleteSmtpToken.json
arcade_hubspot_marketing_api/wrapper_tools/DisassociateCampaignAsset.json
arcade_hubspot_marketing_api/wrapper_tools/DisassociateListFromMarketingEvent.json
arcade_hubspot_marketing_api/wrapper_tools/DisassociateMarketingEventList.json
arcade_hubspot_marketing_api-1.0.0.dist-info/METADATA
arcade_hubspot_marketing_api-1.0.0.dist-info/WHEEL
arcade_hubspot_marketing_api-1.0.0.dist-info/entry_points.txt
arcade_hubspot_marketing_api-1.0.0.dist-info/licenses/LICENSE
arcade_hubspot_marketing_api-1.0.0.dist-info/RECORD
